Workbook
Name Slicer_Country: #N/A

Sheet shoes_sales_dataset
A1: Sale_ID | B1: Date | C1: Brand | D1: Shoe_Type | E1: Color | F1: Country | G1: Sales_Channel | H1: Price_USD | I1: Units_Sold | J1: Revenue_USD | K1: MONTH
A2: S1 | B2: 45985 | C2: Nike | D2: Boots | E2: Blue | F2: UK | G2: Online | H2: 112.4 | I2: 4 | J2: 449.6 | K2: =TEXT(B:B,"MMMM") -> November
A3: S2 | B3: 45729 | C3: Skechers | D3: Boots | E3: Grey | F3: USA | G3: Mall | H3: 239.16 | I3: 4 | J3: 956.64 | K3: =TEXT(B:B,"MMMM") -> March
A4: S3 | B4: 45874 | C4: Nike | D4: Running | E4: White | F4: UK | G4: Mall | H4: 191.04 | I4: 2 | J4: 382.08 | K4: =TEXT(B:B,"MMMM") -> August
A5: S4 | B5: 45966 | C5: New Balance | D5: Casual | E5: Green | F5: UAE | G5: Mall | H5: 161.7 | I5: 1 | J5: 161.7 | K5: =TEXT(B:B,"MMMM") -> November
A6: S5 | B6: 45937 | C6: Adidas | D6: Formal | E6: Grey | F6: France | G6: Online | H6: 64.32 | I6: 14 | J6: 900.48 | K6: =TEXT(B:B,"MMMM") -> October
A7: S6 | B7: 45739 | C7: Puma | D7: Sports | E7: White | F7: UK | G7: Retail Store | H7: 64.32 | I7: 14 | J7: 900.48 | K7: =TEXT(B:B,"MMMM") -> March
A8: S7 | B8: 45710 | C8: Reebok | D8: Running | E8: Blue | F8: Saudi Arabia | G8: Retail Store | H8: 42.78 | I8: 3 | J8: 128.34 | K8: =TEXT(B:B,"MMMM") -> February
A9: S8 | B9: 45967 | C9: Nike | D9: Boots | E9: Red | F9: India | G9: Online | H9: 220.56 | I9: 9 | J9: 1985.04 | K9: =TEXT(B:B,"MMMM") -> November
A10: S9 | B10: 45851 | C10: New Balance | D10: Sports | E10: Green | F10: India | G10: Retail Store | H10: 162.25 | I10: 3 | J10: 486.75 | K10: =TEXT(B:B,"MMMM") -> July
A11: S10 | B11: 45953 | C11: Skechers | D11: Running | E11: Black | F11: UAE | G11: Online | H11: 185.78 | I11: 7 | J11: 1300.46 | K11: =TEXT(B:B,"MMMM") -> October
A12: S11 | B12: 45806 | C12: Adidas | D12: Running | E12: Red | F12: France | G12: Retail Store | H12: 34.53 | I12: 3 | J12: 103.59 | K12: =TEXT(B:B,"MMMM") -> May
A13: S12 | B13: 45983 | C13: Adidas | D13: Sports | E13: Blue | F13: UK | G13: Mall | H13: 243.38 | I13: 12 | J13: 2920.56 | K13: =TEXT(B:B,"MMMM") -> November
... A1001: S1000 | B1001: 45899 | C1001: Puma | D1001: Casual | E1001: Green | F1001: India | G1001: Online | H1001: 128.12 | I1001: 1 | J1001: 128.12 | K1001: =TEXT(B:B,"MMMM") -> August

Sheet ANALYSIS
A1: TOTAL ORDERS | C1: TOTAL SOLD UNITS | E1: MONTH | F1: TOTAL ORDERS | H1: Sale_ID | I1: Date | J1: Brand | K1: Shoe_Type | L1: Color | M1: Country | N1: Sales_Channel | O1: Price_USD | P1: Units_Sold | Q1: Revenue_USD | R1: MONTH
A2: =COUNTA(shoes_sales_dataset[Sale_ID]) -> 1000 | C2: =SUM(shoes_sales_dataset!I:I) -> 10584 | E2: May | F2: =COUNTIF(shoes_sales_dataset!K:K,ANALYSIS!E2) -> 91 | H2: S3 | I2: {=_xlfn.XLOOKUP(H2,shoes_sales_dataset!A:A,shoes_sales_dataset!B:K)} -> 45874 | J2: Nike | K2: Running | L2: White | M2: UK | N2: Mall | O2: 191.04 | P2: 2 | Q2: 382.08 | R2: August
A4: TOTAL REVENUE | C4: AVG UNIT PRICE | E4: MONTH | F4: TOTAL revenue | H4: Sale_ID | I4: Units_Sold | J4: Revenue_USD
A5: =SUM(shoes_sales_dataset!J:J) -> 1453186 | C5: =AVERAGE(shoes_sales_dataset!H:H) -> 137.85642 | E5: May | F5: =SUMIF(shoes_sales_dataset!K:K,ANALYSIS!E5,shoes_sales_dataset!J:J) -> 125637.78 | H5: S10 | I5: =VLOOKUP(H5,shoes_sales_dataset!1:1048576,9,0) -> 7 | J5: =VLOOKUP(H5,shoes_sales_dataset!A:K,10,0) -> 1300.46
E7: MONTH | F7: TOTAL SOLD QUANTITY
E8: May | F8: =SUMIF(shoes_sales_dataset!K:K,ANALYSIS!E8,shoes_sales_dataset!I:I) -> 911
B12: MIN | C12: MAX
A13: REVENUE | B13: =MIN(shoes_sales_dataset!J:J) -> 32.38 | C13: =MAX(shoes_sales_dataset!J:J) -> 4938.4
A14: SOLD QUANTITY | B14: =MIN(shoes_sales_dataset!I:I) -> 1 | C14: =MAX(shoes_sales_dataset!I:I) -> 20

Sheet PIVOT_TABLES
A3: TOTAL ORDERS | B3: MONTH | C3: ORDERS | E3: MONTH | F3: TOTAL SOLD QUANTITY | H3: MONTH | I3: TOTAL REVENUE | K3: Sales channal | L3: TOTAL ORDERS
A4: 713 | B4: Jan | C4: 49 | E4: Jan | F4: 530 | H4: Jan | I4: 77936.83 | K4: Mall | L4: 330
B5: Feb | C5: 66 | E5: Feb | F5: 679 | H5: Feb | I5: 91839.46 | K5: Online | L5: 331
A6: TOTAL SOLD QUANTITY | B6: Mar | C6: 64 | E6: Mar | F6: 646 | H6: Mar | I6: 88887.49 | K6: Retail Store | L6: 339
A7: 7519 | B7: Apr | C7: 48 | E7: Apr | F7: 499 | H7: Apr | I7: 73110.59 | K7: Grand Total | L7: 1000
B8: May | C8: 69 | E8: May | F8: 684 | H8: May | I8: 95162.58
A9: TOTAL REVENUE | B9: Jun | C9: 68 | E9: Jun | F9: 683 | H9: Jun | I9: 88564.75 | K9: sales chennal | L9: TOTAL REVENUE
A10: 1038474.4 | B10: Jul | C10: 66 | E10: Jul | F10: 805 | H10: Jul | I10: 105753.83 | K10: Mall | L10: 479288.58
B11: Aug | C11: 50 | E11: Aug | F11: 439 | H11: Aug | I11: 58483.41 | K11: Online | L11: 467772.32
A12: Average of Price_USD | B12: Sep | C12: 47 | E12: Sep | F12: 512 | H12: Sep | I12: 68405.21 | K12: Retail Store | L12: 506125.13
A13: 137.61682 | B13: Oct | C13: 70 | E13: Oct | F13: 710 | H13: Oct | I13: 100545.94 | K13: Grand Total | L13: 1453186
B14: Nov | C14: 54 | E14: Nov | F14: 622 | H14: Nov | I14: 95552.45
B15: Dec | C15: 62 | E15: Dec | F15: 710 | H15: Dec | I15: 94231.84
E16: Grand Total | F16: 7519 | H16: Grand Total | I16: 1038474.4
A18: BRAND | B18: TOTAL REVENUE | D18: BRAND | E18: TOTAL Units_Sold | G18: BRAND | H18: Average of Price_USD
A19: Adidas | B19: 170427.98 | D19: Skechers | E19: 1264 | G19: Adidas | H19: 135.5922
A20: New Balance | B20: 209266.26 | D20: Reebok | E20: 1335 | G20: New Balance | H20: 147.77866
A21: Nike | B21: 134515.44 | D21: Puma | E21: 1221 | G21: Nike | H21: 130.96769
A22: Puma | B22: 162366.81 | D22: Nike | E22: 1034 | G22: Puma | H22: 134.361
A23: Reebok | B23: 188239.17 | D23: New Balance | E23: 1439 | G23: Reebok | H23: 137.65278
A24: Skechers | B24: 173658.72 | D24: Adidas | E24: 1226 | G24: Skechers | H24: 137.67827
G25: Grand Total | H25: 137.61682
A26: SOLD UNIT | B26: Column Labels
A27: BRAND | B27: Boots | C27: Casual | D27: Formal | E27: Running | F27: Sneakers | G27: Sports | H27: Grand Total
A28: Adidas | B28: 21 | C28: 19 | D28: 17 | E28: 16 | F28: 21 | G28: 15 | H28: 109
A29: New Balance | B29: 29 | C29: 22 | D29: 17 | E29: 17 | F29: 25 | G29: 17 | H29: 127
A30: Nike | B30: 24 | C30: 19 | D30: 17 | E30: 9 | F30: 24 | G30: 11 | H30: 104
A31: Puma | B31: 19 | C31: 19 | D31: 25 | E31: 19 | F31: 16 | G31: 22 | H31: 120
A32: Reebok | B32: 18 | C32: 23 | D32: 21 | E32: 22 | F32: 20 | G32: 22 | H32: 126
A33: Skechers | B33: 28 | C33: 17 | D33: 18 | E33: 27 | F33: 14 | G33: 23 | H33: 127
A34: Grand Total | B34: 139 | C34: 119 | D34: 115 | E34: 110 | F34: 120 | G34: 110 | H34: 713

Sheet DASHB
